llm_judge/__init__.py
llm_judge/llm_judge.py
llm_judger-0.1.0.dist-info/LICENSE
llm_judger-0.1.0.dist-info/METADATA
llm_judger-0.1.0.dist-info/WHEEL
llm_judger-0.1.0.dist-info/entry_points.txt
llm_judger-0.1.0.dist-info/top_level.txt
llm_judger-0.1.0.dist-info/RECORD
