Metadata-Version: 2.1
Name: llm-judger
Version: 0.1.0
Summary: llm's judge each other
Author: Mihai Cosma
License: Apache-2.0
Project-URL: Homepage, https://github.com/wakamex/llm-judge
Project-URL: Changelog, https://github.com/wakamex/llm-judge/releases
Project-URL: Issues, https://github.com/wakamex/llm-judge/issues
Project-URL: CI, https://github.com/wakamex/llm-judge/actions
Classifier: License :: OSI Approved :: Apache Software License
Requires-Python: >=3.9
License-File: LICENSE
Requires-Dist: click
Requires-Dist: llm
Requires-Dist: sqlite-utils
Requires-Dist: tabulate
Provides-Extra: test
Requires-Dist: pytest; extra == "test"
